laser_turtle.py
laser_turtle-1.0.5.dist-info/licenses/LICENSE
laser_turtle-1.0.5.dist-info/METADATA
laser_turtle-1.0.5.dist-info/WHEEL
laser_turtle-1.0.5.dist-info/top_level.txt
laser_turtle-1.0.5.dist-info/RECORD
