Metadata-Version: 2.4
Name: laser_turtle
Version: 1.0.5
Summary: A SVG Turtle package for Laser cutting machine
Author-email: Christophe Declercq <christophe.declercq@univ-reunion.fr>
License-Expression: MIT
Project-URL: Homepage, https://gitlab.com/iremi974/laser-turtle
Classifier: Programming Language :: Python :: 3
Classifier: Operating System :: OS Independent
Requires-Python: >=3.8
License-File: LICENSE
Dynamic: license-file
